my_lambdata/__init__.py
my_lambdata/my_mod.py
my_lambdata/my_script.py
my_lambdata/nulls_func.py
my_lambdata/split_dates_func.py
my_lambdata/state_abbr_to_name_func.py
my_lambdata_khislatz-1.0.dist-info/LICENSE
my_lambdata_khislatz-1.0.dist-info/METADATA
my_lambdata_khislatz-1.0.dist-info/WHEEL
my_lambdata_khislatz-1.0.dist-info/top_level.txt
my_lambdata_khislatz-1.0.dist-info/RECORD
