Metadata-Version: 2.1
Name: my-lambdata-khislatz
Version: 1.0
Summary: A short description
Home-page: https://github.com/Khislatz/lambdata-khislatz
Author: Khislat Zhuraeva
Author-email: your@email.com
License: MIT
Platform: UNKNOWN
